DESCRIPTION
MANIFEST.in
README.txt
setup.cfg
setup.py
LinOTPAdminClientCLI.egg-info/PKG-INFO
LinOTPAdminClientCLI.egg-info/SOURCES.txt
LinOTPAdminClientCLI.egg-info/dependency_links.txt
LinOTPAdminClientCLI.egg-info/top_level.txt
bin/linotpadm.py
doc/linotpadm.py.1
linotpadminclientcli/__init__.py
linotpadminclientcli/clientutils.py
linotpadminclientcli/pytoken-totp.py
linotpadminclientcli/pytoken.template.py
linotpadminclientcli/yubikey.py