Metadata-Version: 1.0
Name: LinOTPAdminClientCLI
Version: 2.10
Summary: LinOTP command-line client
Home-page: https://www.linotp.org
Author: KeyIdentity GmbH
Author-email: linotp@keyidentity.com
License: AGPLv3, (C) KeyIdentity GmbH
Platform: UNKNOWN
